list2csv/__init__.py
list2csv/__init__.pyi
list2csv/_list2csv.py
list2csv/_list2csv.pyi
list2csv-1.3.6.dist-info/LICENSE
list2csv-1.3.6.dist-info/METADATA
list2csv-1.3.6.dist-info/WHEEL
list2csv-1.3.6.dist-info/top_level.txt
list2csv-1.3.6.dist-info/RECORD
