Metadata-Version: 2.1
Name: list2csv
Version: 1.3.6
Summary: A simple package intended to help write iterables of objects to CSV files
Home-page: https://github.com/James-Ansley/list2csv
Author: James Finnie-Ansley
License: UNKNOWN
Platform: UNKNOWN
Classifier: Development Status :: 5 - Production/Stable
Classifier: Topic :: Utilities
Classifier: Intended Audience :: Developers
Classifier: Programming Language :: Python :: 3
Classifier: License :: OSI Approved :: MIT License
Classifier: Operating System :: OS Independent
Requires-Python: >=3.6
License-File: LICENSE
